README.md
setup.py
adman/__init__.py
adman/__main__.py
adman/adman.py
adman/assign.py
adman/cli.py
adman/config.py
adman/email.py
adman/kerberos.py
adman/ldapfilter.py
adman/ldapobj.py
adman/locate.py
adman/paths.py
adman/pwexpire.py
adman/smbacl.py
adman/staleacct.py
adman/state.py
adman/types.py
adman/userdir.py
adman/util.py
adman/version.py
adman.egg-info/PKG-INFO
adman.egg-info/SOURCES.txt
adman.egg-info/dependency_links.txt
adman.egg-info/entry_points.txt
adman.egg-info/requires.txt
adman.egg-info/top_level.txt